Hajime/__init__.py
Hajime/core.py
Hajime/test.py
hajime-2.2.dist-info/licenses/LICENSE
hajime-2.2.dist-info/METADATA
hajime-2.2.dist-info/WHEEL
hajime-2.2.dist-info/top_level.txt
hajime-2.2.dist-info/RECORD
