Metadata-Version: 2.4
Name: Hajime
Version: 2.2
Summary: Amazing Website Framework
Home-page: https://Hajime.pythonanywhere.com
Author: Franciszek Czajkowski
Project-URL: Source, https://github.com/FCzajkowski/Hajime
Project-URL: Documentation, https://Hajime.pythonanywhere.com/Documentation
Classifier: Programming Language :: Python :: 3
Classifier: License :: OSI Approved :: MIT License
License-File: LICENSE
Requires-Dist: sqlalchemy
Requires-Dist: termcolor
Requires-Dist: websockets
Dynamic: author
Dynamic: classifier
Dynamic: home-page
Dynamic: license-file
Dynamic: project-url
Dynamic: requires-dist
Dynamic: summary
